frater/__init__.py
frater/client/__init__.py
frater/client/api.py
frater/client/component.py
frater/client/system.py
frater/component/__init__.py
frater/component/builder/__init__.py
frater/component/builder/builder.py
frater/component/component/__init__.py
frater/component/component/batch_component.py
frater/component/component/component.py
frater/component/component/input_component.py
frater/component/component/io_component.py
frater/component/component/output_component.py
frater/component/component/window_component.py
frater/component/manager/__init__.py
frater/component/manager/manager.py
frater/component/manager/thread.py
frater/config/__init__.py
frater/config/config.py
frater/data/__init__.py
frater/data/category/__init__.py
frater/data/category/category.py
frater/data/data_store/__init__.py
frater/data/data_store/file_store/__init__.py
frater/data/data_store/file_store/file_store.py
frater/data/data_store/file_store/image_store.py
frater/data/data_type/__init__.py
frater/data/data_type/data_type.py
frater/data/data_type/factory.py
frater/data/dataset/__init__.py
frater/data/dataset/dataset.py
frater/data/dataset/factory.py
frater/dependency/__init__.py
frater/dependency/dependency.py
frater/factory/__init__.py
frater/factory/factory.py
frater/factory/object_factory.py
frater/io/__init__.py
frater/io/deserializers.py
frater/io/serializers.py
frater/logging/__init__.py
frater/logging/logger.py
frater/logging/summary.py
frater/logging/handler/__init__.py
frater/logging/handler/config.py
frater/logging/handler/factory.py
frater/logging/handler/kafka.py
frater/logging/handler/standard.py
frater/server/__init__.py
frater/server/component.py
frater/server/middleware.py
frater/server/server_manager.py
frater/server/system.py
frater/stream/__init__.py
frater/stream/build.py
frater/stream/factory.py
frater/stream/json.py
frater/stream/kafka.py
frater/stream/log.py
frater/stream/mongo.py
frater/stream/stream.py
frater/stream/stream_state.py
frater/system/__init__.py
frater-0.3.1.15.dist-info/LICENSE
frater-0.3.1.15.dist-info/METADATA
frater-0.3.1.15.dist-info/WHEEL
frater-0.3.1.15.dist-info/top_level.txt
frater-0.3.1.15.dist-info/RECORD
