Metadata-Version: 2.1
Name: frater
Version: 0.3.1.15
Summary: A Machine Learning and Data-Driven Systems Framework and Toolkit
Home-page: https://github.com/frater-sdk/frater
Author: John Henning
Author-email: john.l.henning@ibm.com
License: MIT
Platform: UNKNOWN
Requires-Python: >=3.6
Requires-Dist: pymongo
Requires-Dist: flask
Requires-Dist: requests
Requires-Dist: pyyaml
Requires-Dist: kafka-python
Requires-Dist: pillow
Requires-Dist: dataclasses-json
Requires-Dist: inflection
